[
    {
        "nodeID": 1,
        "nodeTier": 1,
        "characteristics": {
            "cpu": 25593,
            "memory": 2344,
            "disk": 14774.1,
            "platform": "OS3",
            "reliabilityScore": 1
        }
    },
    {
        "nodeID": 2,
        "nodeTier": 1,
        "characteristics": {
            "cpu": 29561,
            "memory": 2681,
            "disk": 17740.7,
            "platform": "OS4",
            "reliabilityScore": 1
        }
    },
    {
        "nodeID": 3,
        "nodeTier": 1,
        "characteristics": {
            "cpu": 29594,
            "memory": 3187,
            "disk": 28666.5,
            "platform": "OS4",
            "reliabilityScore": 1
        }
    },
    {
        "nodeID": 4,
        "nodeTier": 1,
        "characteristics": {
            "cpu": 28379,
            "memory": 2450,
            "disk": 10747.7,
            "platform": "OS4",
            "reliabilityScore": 1
        }
    },
    {
        "nodeID": 5,
        "nodeTier": 1,
        "characteristics": {
            "cpu": 29000,
            "memory": 2981,
            "disk": 23783.7,
            "platform": "OS4",
            "reliabilityScore": 1
        }
    },
    {
        "nodeID": 6,
        "nodeTier": 1,
        "characteristics": {
            "cpu": 28225,
            "memory": 3827,
            "disk": 9567.7,
            "platform": "OS1",
            "reliabilityScore": 1
        }
    },
    {
        "nodeID": 7,
        "nodeTier": 1,
        "characteristics": {
            "cpu": 28976,
            "memory": 2604,
            "disk": 31664.8,
            "platform": "OS3",
            "reliabilityScore": 1
        }
    },
    {
        "nodeID": 8,
        "nodeTier": 1,
        "characteristics": {
            "cpu": 25899,
            "memory": 3293,
            "disk": 9516.9,
            "platform": "OS4",
            "reliabilityScore": 1
        }
    },
    {
        "nodeID": 9,
        "nodeTier": 2,
        "characteristics": {
            "cpu": 31566,
            "memory": 5066,
            "disk": 93690.3,
            "platform": "OS3",
            "reliabilityScore": 1
        }
    },
    {
        "nodeID": 10,
        "nodeTier": 2,
        "characteristics": {
            "cpu": 30861,
            "memory": 4803,
            "disk": 86125.5,
            "platform": "OS1",
            "reliabilityScore": 1
        }
    },
    {
        "nodeID": 11,
        "nodeTier": 2,
        "characteristics": {
            "cpu": 32530,
            "memory": 6038,
            "disk": 59050,
            "platform": "OS4",
            "reliabilityScore": 1
        }
    },
    {
        "nodeID": 12,
        "nodeTier": 2,
        "characteristics": {
            "cpu": 30392,
            "memory": 5478,
            "disk": 115340.7,
            "platform": "OS2",
            "reliabilityScore": 1
        }
    },
    {
        "nodeID": 13,
        "nodeTier": 3,
        "characteristics": {
            "cpu": 42221,
            "memory": 13976,
            "disk": 168929.1,
            "platform": "OS4",
            "reliabilityScore": 1
        }
    },
    {
        "nodeID": 14,
        "nodeTier": 3,
        "characteristics": {
            "cpu": 38983,
            "memory": 11103,
            "disk": 136912.9,
            "platform": "OS1",
            "reliabilityScore": 1
        }
    }
]